app/__init__.py
app/__main__.py
pyappdir-0.0.1b1.dist-info/LICENSE
pyappdir-0.0.1b1.dist-info/METADATA
pyappdir-0.0.1b1.dist-info/WHEEL
pyappdir-0.0.1b1.dist-info/top_level.txt
pyappdir-0.0.1b1.dist-info/RECORD
